utils_cv/__init__.py
utils_cv/utils_benchmark.py
utils_cv/utils_box.py
utils_cv/utils_dataset.py
utils_cv/utils_file.py
utils_cv/utils_geometry.py
utils_cv/utils_image.py
utils_cv/utils_jupyter.py
utils_cv/utils_layout.py
utils_cv/utils_benchmark/__init__.py
utils_cv/utils_benchmark/end2end.py
utils_cv/utils_benchmark/text_detection.py
utils_cv_baiyigali-0.0.11.8.dist-info/LICENSE
utils_cv_baiyigali-0.0.11.8.dist-info/METADATA
utils_cv_baiyigali-0.0.11.8.dist-info/WHEEL
utils_cv_baiyigali-0.0.11.8.dist-info/top_level.txt
utils_cv_baiyigali-0.0.11.8.dist-info/RECORD
