Metadata-Version: 2.1
Name: utils-cv-baiyigali
Version: 0.0.11.8
Summary: A small example package
Home-page: https://github.com/pypa/sampleproject
Author: baiyigali
Author-email: 1304646911@qq.com
License: UNKNOWN
Project-URL: Bug Tracker, https://github.com/pypa/sampleproject/issues
Platform: UNKNOWN
Classifier: Programming Language :: Python :: 3
Classifier: License :: OSI Approved :: MIT License
Classifier: Operating System :: OS Independent
Requires-Python: >=3.6
License-File: LICENSE
Requires-Dist: numpy
Requires-Dist: pandas
Requires-Dist: nltk
